timeloop/__init__.py
timeloop/app.py
timeloop/exceptions.py
timeloop/helpers.py
timeloop/job.py
timeloop_ng-1.0.0.dist-info/LICENSE
timeloop_ng-1.0.0.dist-info/METADATA
timeloop_ng-1.0.0.dist-info/WHEEL
timeloop_ng-1.0.0.dist-info/top_level.txt
timeloop_ng-1.0.0.dist-info/RECORD
