Metadata-Version: 2.1
Name: timeloop-ng
Version: 1.0.0
Summary: An elegant way to run period tasks.
Home-page: https://github.com/tuergeist/timeloop
Author: Sankalp Jonna, Christoph Becker
Author-email: tuergeist@gmail.com
License: MIT
Keywords: tasks,jobs,periodic task,interval,periodic job,flask style,decorator
Platform: UNKNOWN
License-File: LICENSE
